{
	"_id": "missionaries/Carter-Simeon_1794-1869",
	name: {
		"last": "Carter",
		"first": "Simeon"
	},
	"birth": { "year": 1794 },
	"death": { "year": 1869 },
	"family": [
		{ "father": { "last": "", "first": "" } },
		{ "mother": { "last": "", "first": "" } },
		{ "sibling": { "last": "", "first": "" } },
		{ "spouse": { "last": "", "first": "" } },
		{ "child": { "last": "", "first": "" } }
	],
	"missions": [
		{
			"start": { "year": "#", "month": "#", "day": "#" },
			"end": { "year": "#", "month": "#", "day": "#" },
			"companions": [],
			"locations": [],
			"recipients": [],
			"sources": []
		}
	],
	"sources": []
}